{
  "generated_at": "2026-03-16T13:32:37.735034+00:00",
  "days": 1,
  "total_patches": 16,
  "series": [
    {
      "title": "kho: history: track previous kernel version and kexec boot count",
      "author": "Breno Leitao <leitao@debian.org>",
      "patches": [
        {
          "title": "[PATCH v9 0/6] kho: history: track previous kernel version and kexec boot count",
          "link": "https://lore.kernel.org/linux-mm/20260316-kho-v9-0-ed6dcd951988@debian.org/"
        },
        {
          "title": "[PATCH v9 1/6] kho: add size parameter to kho_add_subtree()",
          "link": "https://lore.kernel.org/linux-mm/20260316-kho-v9-1-ed6dcd951988@debian.org/"
        },
        {
          "title": "[PATCH v9 2/6] kho: rename fdt parameter to blob in kho_add/remove_subtree()",
          "link": "https://lore.kernel.org/linux-mm/20260316-kho-v9-2-ed6dcd951988@debian.org/"
        },
        {
          "title": "[PATCH v9 3/6] kho: persist blob size in KHO FDT",
          "link": "https://lore.kernel.org/linux-mm/20260316-kho-v9-3-ed6dcd951988@debian.org/"
        },
        {
          "title": "[PATCH v9 4/6] kho: fix kho_in_debugfs_init() to handle non-FDT blobs",
          "link": "https://lore.kernel.org/linux-mm/20260316-kho-v9-4-ed6dcd951988@debian.org/"
        },
        {
          "title": "[PATCH v9 5/6] kho: kexec-metadata: track previous kernel chain",
          "link": "https://lore.kernel.org/linux-mm/20260316-kho-v9-5-ed6dcd951988@debian.org/"
        },
        {
          "title": "[PATCH v9 6/6] kho: document kexec-metadata tracking feature",
          "link": "https://lore.kernel.org/linux-mm/20260316-kho-v9-6-ed6dcd951988@debian.org/"
        }
      ],
      "patch_count": 6,
      "link": "https://lore.kernel.org/linux-mm/20260316-kho-v9-0-ed6dcd951988@debian.org/",
      "updated": "Mon, 16 Mar 2026 04:54:30 -0700",
      "subsystems": [
        "docs",
        "include",
        "kernel",
        "memblock",
        "tests"
      ],
      "review": {
        "summary": "Review timed out.",
        "issues": [],
        "verdict": "skip"
      },
      "fetch_date": "2026-03-16"
    },
    {
      "title": "kernel/fork: validate exit_signal in kernel_clone()",
      "author": "Deepanshu Kartikey <kartikey406@gmail.com>",
      "patches": [
        {
          "title": "[PATCH v2] kernel/fork: validate exit_signal in kernel_clone()",
          "link": "https://lore.kernel.org/linux-mm/20260316104536.558108-1-kartikey406@gmail.com/"
        }
      ],
      "patch_count": 1,
      "link": "https://lore.kernel.org/linux-mm/20260316104536.558108-1-kartikey406@gmail.com/",
      "updated": "Mon, 16 Mar 2026 16:15:36 +0530",
      "subsystems": [
        "kernel"
      ],
      "review": {
        "summary": "Review timed out.",
        "issues": [],
        "verdict": "skip"
      },
      "fetch_date": "2026-03-16"
    },
    {
      "title": "mm: Free contiguous order-0 pages efficiently",
      "author": "Muhammad Usama Anjum <usama.anjum@arm.com>",
      "patches": [
        {
          "title": "[PATCH v2 0/3] mm: Free contiguous order-0 pages efficiently",
          "link": "https://lore.kernel.org/linux-mm/20260316113209.945853-1-usama.anjum@arm.com/"
        },
        {
          "title": "[PATCH v2 1/3] mm/page_alloc: Optimize free_contig_range()",
          "link": "https://lore.kernel.org/linux-mm/20260316113209.945853-2-usama.anjum@arm.com/"
        },
        {
          "title": "[PATCH v2 2/3] vmalloc: Optimize vfree",
          "link": "https://lore.kernel.org/linux-mm/20260316113209.945853-3-usama.anjum@arm.com/"
        },
        {
          "title": "[PATCH v2 3/3] mm/page_alloc: Optimize __free_contig_frozen_range()",
          "link": "https://lore.kernel.org/linux-mm/20260316113209.945853-4-usama.anjum@arm.com/"
        }
      ],
      "patch_count": 3,
      "link": "https://lore.kernel.org/linux-mm/20260316113209.945853-1-usama.anjum@arm.com/",
      "updated": "Mon, 16 Mar 2026 11:31:41 +0000",
      "subsystems": [
        "include",
        "page_alloc",
        "vmalloc"
      ],
      "review": {
        "summary": "Review timed out.",
        "issues": [],
        "verdict": "skip"
      },
      "fetch_date": "2026-03-16"
    },
    {
      "title": "mm/userfaultfd: re-validate vma in mfill_atomic() loop under CONFIG_PER_VMA_LOCK",
      "author": "Deepanshu Kartikey <kartikey406@gmail.com>",
      "patches": [
        {
          "title": "[PATCH] mm/userfaultfd: re-validate vma in mfill_atomic() loop under CONFIG_PER_VMA_LOCK",
          "link": "https://lore.kernel.org/linux-mm/20260316070039.549506-1-kartikey406@gmail.com/"
        }
      ],
      "patch_count": 1,
      "link": "https://lore.kernel.org/linux-mm/20260316070039.549506-1-kartikey406@gmail.com/",
      "updated": "Mon, 16 Mar 2026 12:30:39 +0530",
      "subsystems": [
        "userfaultfd"
      ],
      "review": {
        "summary": "Review timed out.",
        "issues": [],
        "verdict": "skip"
      },
      "fetch_date": "2026-03-16"
    },
    {
      "title": "mm/memcontrol: batch memcg charging in __memcg_slab_post_alloc_hook",
      "author": "Hui Zhu <hui.zhu@linux.dev>",
      "patches": [
        {
          "title": "[PATCH mm-unstable] mm/memcontrol: batch memcg charging in __memcg_slab_post_alloc_hook",
          "link": "https://lore.kernel.org/linux-mm/20260316084839.1342163-1-hui.zhu@linux.dev/"
        }
      ],
      "patch_count": 1,
      "link": "https://lore.kernel.org/linux-mm/20260316084839.1342163-1-hui.zhu@linux.dev/",
      "updated": "Mon, 16 Mar 2026 16:48:38 +0800",
      "subsystems": [
        "memcontrol"
      ],
      "review": {
        "summary": "Review timed out.",
        "issues": [],
        "verdict": "skip"
      },
      "fetch_date": "2026-03-16"
    },
    {
      "title": "Docs: mmap_prepare: don't italicize structs",
      "author": "Randy Dunlap <rdunlap@infradead.org>",
      "patches": [
        {
          "title": "[PATCH] Docs: mmap_prepare: don't italicize structs",
          "link": "https://lore.kernel.org/linux-mm/20260315224506.1973566-1-rdunlap@infradead.org/"
        }
      ],
      "patch_count": 1,
      "link": "https://lore.kernel.org/linux-mm/20260315224506.1973566-1-rdunlap@infradead.org/",
      "updated": "Sun, 15 Mar 2026 15:45:06 -0700",
      "subsystems": [],
      "review": {
        "summary": "Review timed out.",
        "issues": [],
        "verdict": "skip"
      },
      "fetch_date": "2026-03-15"
    },
    {
      "title": "selftests/mm: skip several tests when thp is not available",
      "author": "Chunyu Hu <chuhu@redhat.com>",
      "patches": [
        {
          "title": "[PATCH v2 0/5] selftests/mm: skip several tests when thp is not available",
          "link": "https://lore.kernel.org/linux-mm/20260316044335.1390608-1-chuhu@redhat.com/"
        },
        {
          "title": "[PATCH v2 1/5] selftests/mm/guard-regions: skip collapse test when thp not enabled",
          "link": "https://lore.kernel.org/linux-mm/20260316044335.1390608-2-chuhu@redhat.com/"
        },
        {
          "title": "[PATCH v2 2/5] selftests/mm: soft-dirty: skip two tests when thp is not available",
          "link": "https://lore.kernel.org/linux-mm/20260316044335.1390608-3-chuhu@redhat.com/"
        },
        {
          "title": "[PATCH v2 3/5] selftests/mm: move write_file helper to vm_util",
          "link": "https://lore.kernel.org/linux-mm/20260316044335.1390608-4-chuhu@redhat.com/"
        },
        {
          "title": "[PATCH v2 4/5] selftests/mm: split_huge_page_test: skip the test when thp is not available",
          "link": "https://lore.kernel.org/linux-mm/20260316044335.1390608-5-chuhu@redhat.com/"
        },
        {
          "title": "[PATCH v2 5/5] selftests/mm: transhuge_stress: skip the test when thp not available",
          "link": "https://lore.kernel.org/linux-mm/20260316044335.1390608-6-chuhu@redhat.com/"
        }
      ],
      "patch_count": 5,
      "link": "https://lore.kernel.org/linux-mm/20260316044335.1390608-1-chuhu@redhat.com/",
      "updated": "Mon, 16 Mar 2026 12:43:30 +0800",
      "subsystems": [
        "tests"
      ],
      "review": {
        "summary": "Review timed out.",
        "issues": [],
        "verdict": "skip"
      },
      "fetch_date": "2026-03-16"
    },
    {
      "title": "Migrate on fault for device pages",
      "author": "mpenttil@redhat.com",
      "patches": [
        {
          "title": "[PATCH v6 0/6] Migrate on fault for device pages",
          "link": "https://lore.kernel.org/linux-mm/20260316062407.3354636-1-mpenttil@redhat.com/"
        },
        {
          "title": "[PATCH v6 1/6] mm:/Kconfig changes for migrate on fault for device pages",
          "link": "https://lore.kernel.org/linux-mm/20260316062407.3354636-2-mpenttil@redhat.com/"
        },
        {
          "title": "[PATCH v6 2/6] mm: Add helper to convert HMM pfn to migrate pfn",
          "link": "https://lore.kernel.org/linux-mm/20260316062407.3354636-3-mpenttil@redhat.com/"
        },
        {
          "title": "[PATCH v6 3/6] mm/hmm: do the plumbing for HMM to participate in migration",
          "link": "https://lore.kernel.org/linux-mm/20260316062407.3354636-4-mpenttil@redhat.com/"
        },
        {
          "title": "[PATCH v6 4/6] mm: setup device page migration in HMM pagewalk",
          "link": "https://lore.kernel.org/linux-mm/20260316062407.3354636-5-mpenttil@redhat.com/"
        },
        {
          "title": "[PATCH v6 5/6] mm: add new testcase for the migrate on fault case",
          "link": "https://lore.kernel.org/linux-mm/20260316062407.3354636-6-mpenttil@redhat.com/"
        },
        {
          "title": "[PATCH v6 6/6] mm:/migrate_device.c: remove migrate_vma_collect_*()",
          "link": "https://lore.kernel.org/linux-mm/20260316062407.3354636-7-mpenttil@redhat.com/"
        }
      ],
      "patch_count": 6,
      "link": "https://lore.kernel.org/linux-mm/20260316062407.3354636-1-mpenttil@redhat.com/",
      "updated": "Mon, 16 Mar 2026 08:24:01 +0200",
      "subsystems": [
        "Kconfig",
        "hmm",
        "include",
        "migrate_device",
        "tests"
      ],
      "review": {
        "summary": "Review timed out.",
        "issues": [],
        "verdict": "skip"
      },
      "fetch_date": "2026-03-16"
    },
    {
      "title": "[LSF/MM/BPF TOPIC]  mm/mempolicy: introduce socket-aware weighted interleave",
      "author": "Rakie Kim <rakie.kim@sk.com>",
      "patches": [
        {
          "title": "[LSF/MM/BPF TOPIC] [RFC PATCH 0/4] mm/mempolicy: introduce socket-aware weighted interleave",
          "link": "https://lore.kernel.org/linux-mm/20260316051258.246-1-rakie.kim@sk.com/"
        },
        {
          "title": "[RFC PATCH 1/4] mm/numa: introduce nearest_nodes_nodemask()",
          "link": "https://lore.kernel.org/linux-mm/20260316051258.246-2-rakie.kim@sk.com/"
        },
        {
          "title": "[RFC PATCH 2/4] mm/memory-tiers: introduce socket-aware topology management for NUMA nodes",
          "link": "https://lore.kernel.org/linux-mm/20260316051258.246-3-rakie.kim@sk.com/"
        },
        {
          "title": "[RFC PATCH 3/4] mm/memory-tiers: register CXL nodes to socket-aware packages via initiator",
          "link": "https://lore.kernel.org/linux-mm/20260316051258.246-4-rakie.kim@sk.com/"
        },
        {
          "title": "[RFC PATCH 4/4] mm/mempolicy: enhance weighted interleave with socket-aware locality",
          "link": "https://lore.kernel.org/linux-mm/20260316051258.246-5-rakie.kim@sk.com/"
        }
      ],
      "patch_count": 4,
      "link": "https://lore.kernel.org/linux-mm/20260316051258.246-1-rakie.kim@sk.com/",
      "updated": "Mon, 16 Mar 2026 14:12:48 +0900",
      "subsystems": [
        "drivers",
        "include",
        "memory-tiers",
        "mempolicy"
      ],
      "review": {
        "summary": "Review timed out.",
        "issues": [],
        "verdict": "skip"
      },
      "fetch_date": "2026-03-16"
    },
    {
      "title": "userfaultfd: unassigned vma leads to a potential unreleased locks",
      "author": "Edward Adam Davis <eadavis@qq.com>",
      "patches": [
        {
          "title": "[PATCH next] userfaultfd: unassigned vma leads to a potential unreleased locks",
          "link": "https://lore.kernel.org/linux-mm/tencent_C43C1BB425D6BA16BB6533FC9E001BC64B08@qq.com/"
        }
      ],
      "patch_count": 1,
      "link": "https://lore.kernel.org/linux-mm/tencent_C43C1BB425D6BA16BB6533FC9E001BC64B08@qq.com/",
      "updated": "Mon, 16 Mar 2026 11:11:03 +0800",
      "subsystems": [
        "userfaultfd"
      ],
      "review": {
        "summary": "Review timed out.",
        "issues": [],
        "verdict": "skip"
      },
      "fetch_date": "2026-03-16"
    },
    {
      "title": "zram: propagate read_from_bdev_async() errors",
      "author": "Sergey Senozhatsky <senozhatsky@chromium.org>",
      "patches": [
        {
          "title": "[PATCH] zram: propagate read_from_bdev_async() errors",
          "link": "https://lore.kernel.org/linux-mm/20260316015354.114465-1-senozhatsky@chromium.org/"
        }
      ],
      "patch_count": 1,
      "link": "https://lore.kernel.org/linux-mm/20260316015354.114465-1-senozhatsky@chromium.org/",
      "updated": "Mon, 16 Mar 2026 10:53:32 +0900",
      "subsystems": [
        "drivers"
      ],
      "review": {
        "summary": "Review timed out.",
        "issues": [],
        "verdict": "skip"
      },
      "fetch_date": "2026-03-16"
    },
    {
      "title": "mm/damon: let DAMON be paused and resumed",
      "author": "SeongJae Park <sj@kernel.org>",
      "patches": [
        {
          "title": "[RFC PATCH 00/10] mm/damon: let DAMON be paused and resumed",
          "link": "https://lore.kernel.org/linux-mm/20260315210012.94846-1-sj@kernel.org/"
        },
        {
          "title": "[RFC PATCH 01/10] mm/damon/core: introduce damon_ctx->paused",
          "link": "https://lore.kernel.org/linux-mm/20260315210012.94846-2-sj@kernel.org/"
        },
        {
          "title": "[RFC PATCH 02/10] mm/damon/sysfs: add pause file under context dir",
          "link": "https://lore.kernel.org/linux-mm/20260315210012.94846-3-sj@kernel.org/"
        },
        {
          "title": "[RFC PATCH 03/10] Docs/mm/damon/design: update for context pause/resume feature",
          "link": "https://lore.kernel.org/linux-mm/20260315210012.94846-4-sj@kernel.org/"
        },
        {
          "title": "[RFC PATCH 04/10] Docs/admin-guide/mm/damon/usage: update for pause file",
          "link": "https://lore.kernel.org/linux-mm/20260315210012.94846-5-sj@kernel.org/"
        },
        {
          "title": "[RFC PATCH 05/10] Docs/ABI/damon: update for pause sysfs file",
          "link": "https://lore.kernel.org/linux-mm/20260315210012.94846-6-sj@kernel.org/"
        },
        {
          "title": "[RFC PATCH 06/10] mm/damon/tests/core-kunit: test pause commitment",
          "link": "https://lore.kernel.org/linux-mm/20260315210012.94846-7-sj@kernel.org/"
        },
        {
          "title": "[RFC PATCH 07/10] selftests/damon/_damon_sysfs: support pause file staging",
          "link": "https://lore.kernel.org/linux-mm/20260315210012.94846-8-sj@kernel.org/"
        },
        {
          "title": "[RFC PATCH 08/10] selftests/damon/drgn_dump_damon_status: dump pause",
          "link": "https://lore.kernel.org/linux-mm/20260315210012.94846-9-sj@kernel.org/"
        },
        {
          "title": "[RFC PATCH 09/10] selftests/damon/sysfs.py: check pause on assert_ctx_committed()",
          "link": "https://lore.kernel.org/linux-mm/20260315210012.94846-10-sj@kernel.org/"
        },
        {
          "title": "[RFC PATCH 10/10] selftets/damon/sysfs.py: pause DAMON before dumping status",
          "link": "https://lore.kernel.org/linux-mm/20260315210012.94846-11-sj@kernel.org/"
        }
      ],
      "patch_count": 10,
      "link": "https://lore.kernel.org/linux-mm/20260315210012.94846-1-sj@kernel.org/",
      "updated": "Sun, 15 Mar 2026 13:59:59 -0700",
      "subsystems": [
        "damon/core",
        "damon/sysfs",
        "damon/tests/core-kunit",
        "docs",
        "include",
        "tests"
      ],
      "review": {
        "summary": "Review timed out.",
        "issues": [],
        "verdict": "skip"
      },
      "fetch_date": "2026-03-15"
    },
    {
      "title": "mm/damon/stat: monitor all System RAM resources",
      "author": "SeongJae Park <sj@kernel.org>",
      "patches": [
        {
          "title": "[PATCH v2] mm/damon/stat: monitor all System RAM resources",
          "link": "https://lore.kernel.org/linux-mm/20260315162717.80870-1-sj@kernel.org/"
        }
      ],
      "patch_count": 1,
      "link": "https://lore.kernel.org/linux-mm/20260315162717.80870-1-sj@kernel.org/",
      "updated": "Sun, 15 Mar 2026 09:27:15 -0700",
      "subsystems": [
        "damon/stat"
      ],
      "review": {
        "summary": "Review timed out.",
        "issues": [],
        "verdict": "skip"
      },
      "fetch_date": "2026-03-15"
    },
    {
      "title": "mm/mglru: fix cgroup OOM during MGLRU state switching",
      "author": "Leno Hou via B4 Relay <devnull+lenohou.gmail.com@kernel.org>",
      "patches": [
        {
          "title": "[PATCH v3 0/2] mm/mglru: fix cgroup OOM during MGLRU state switching",
          "link": "https://lore.kernel.org/linux-mm/20260316-b4-switch-mglru-v2-v3-0-c846ce9a2321@gmail.com/"
        },
        {
          "title": "[PATCH v3 1/2] mm/mglru: fix cgroup OOM during MGLRU state switching",
          "link": "https://lore.kernel.org/linux-mm/20260316-b4-switch-mglru-v2-v3-1-c846ce9a2321@gmail.com/"
        },
        {
          "title": "[PATCH v3 2/2] mm/mglru: maintain workingset refault context across state transitions",
          "link": "https://lore.kernel.org/linux-mm/20260316-b4-switch-mglru-v2-v3-2-c846ce9a2321@gmail.com/"
        }
      ],
      "patch_count": 2,
      "link": "https://lore.kernel.org/linux-mm/20260316-b4-switch-mglru-v2-v3-0-c846ce9a2321@gmail.com/",
      "updated": "Mon, 16 Mar 2026 02:18:27 +0800",
      "subsystems": [
        "include",
        "rmap",
        "swap",
        "vmscan",
        "workingset"
      ],
      "review": {
        "summary": "Review timed out.",
        "issues": [],
        "verdict": "skip"
      },
      "fetch_date": "2026-03-16"
    },
    {
      "title": "Docs/mm/damon: document exclusivity of special-purpose modules",
      "author": "SeongJae Park <sj@kernel.org>",
      "patches": [
        {
          "title": "[PATCH v2] Docs/mm/damon: document exclusivity of special-purpose modules",
          "link": "https://lore.kernel.org/linux-mm/20260315162945.80994-1-sj@kernel.org/"
        }
      ],
      "patch_count": 1,
      "link": "https://lore.kernel.org/linux-mm/20260315162945.80994-1-sj@kernel.org/",
      "updated": "Sun, 15 Mar 2026 09:29:44 -0700",
      "subsystems": [
        "docs"
      ],
      "review": {
        "summary": "Review timed out.",
        "issues": [],
        "verdict": "skip"
      },
      "fetch_date": "2026-03-15"
    },
    {
      "title": "mm/mempolicy: NUMA mempolicy mismatch during remote access",
      "author": "Lin Ruifeng <linruifeng4@huawei.com>",
      "patches": [
        {
          "title": "[RFC PATCH] mm/mempolicy: NUMA mempolicy mismatch during remote access",
          "link": "https://lore.kernel.org/linux-mm/20260316120424.1535575-1-linruifeng4@huawei.com/"
        }
      ],
      "patch_count": 1,
      "link": "https://lore.kernel.org/linux-mm/20260316120424.1535575-1-linruifeng4@huawei.com/",
      "updated": "Mon, 16 Mar 2026 20:04:24 +0800",
      "subsystems": [],
      "review": {
        "summary": "Review timed out.",
        "issues": [],
        "verdict": "skip"
      },
      "fetch_date": "2026-03-16"
    }
  ]
}